fild_cfg/__init__.py
fild_cfg/config.py
fild_cfg-0.0.1.dist-info/LICENSE
fild_cfg-0.0.1.dist-info/METADATA
fild_cfg-0.0.1.dist-info/WHEEL
fild_cfg-0.0.1.dist-info/top_level.txt
fild_cfg-0.0.1.dist-info/RECORD
